{"name":"alice-c_nobel-database","title":"Nobel-Database","description":"Nobel-Database\n\n# Nobel-Database","homepage":"https://data.world/alice-c/nobel-database","license":"Other","resources":[{"name":"award_categories","schema":{"fields":[{"name":"category","title":"Category","type":"string","rdfType":"http://www.w3.org/2001/XMLSchema#string","dwSourceId":"category"},{"name":"average_age_of_laureates","title":"Average age of laureates","type":"integer","rdfType":"http://www.w3.org/2001/XMLSchema#integer","dwSourceId":"average_age_of_laureates"},{"name":"prizes_won_by_women","title":"Prizes won by women","type":"integer","rdfType":"http://www.w3.org/2001/XMLSchema#integer","dwSourceId":"prizes_won_by_women"},{"name":"prizes_won_by_men","title":"Prizes won by men","type":"integer","rdfType":"http://www.w3.org/2001/XMLSchema#integer","dwSourceId":"prizes_won_by_men"},{"name":"percentage_prizes_won_by_women","title":"Percentage prizes won by women","type":"number","rdfType":"http://www.w3.org/2001/XMLSchema#decimal","dwSourceId":"percentage_prizes_won_by_women"},{"name":"percentage_prizes_won_by_men","title":"Percentage prizes won by men","type":"number","rdfType":"http://www.w3.org/2001/XMLSchema#decimal","dwSourceId":"percentage_prizes_won_by_men"},{"name":"remove_average_female_winners_all_countries","title":"REMOVE Average Female Winners (All Countries)","type":"integer","rdfType":"http://www.w3.org/2001/XMLSchema#integer","dwSourceId":"remove_average_female_winners_all_countries"},{"name":"remove_average_female_winners_all_countries_2","title":"REMOVE Average Female Winners (All Countries) (%)","type":"number","rdfType":"http://www.w3.org/2001/XMLSchema#decimal","dwSourceId":"remove_average_female_winners_all_countries_2"}]},"path":"data/award_categories.csv","format":"csv"},{"name":"countries","schema":{"fields":[{"name":"country","title":"Country","type":"string","rdfType":"http://www.w3.org/2001/XMLSchema#string","dwSourceId":"country"},{"name":"number_of_prizes","title":"Number of prizes","type":"integer","rdfType":"http://www.w3.org/2001/XMLSchema#integer","dwSourceId":"number_of_prizes"},{"name":"average_age_of_laureates","title":"Average age of laureates","type":"integer","rdfType":"http://www.w3.org/2001/XMLSchema#integer","dwSourceId":"average_age_of_laureates"},{"name":"prizes_won_by_women","title":"Prizes won by women","type":"integer","rdfType":"http://www.w3.org/2001/XMLSchema#integer","dwSourceId":"prizes_won_by_women"},{"name":"prizes_won_by_men","title":"Prizes won by men","type":"integer","rdfType":"http://www.w3.org/2001/XMLSchema#integer","dwSourceId":"prizes_won_by_men"},{"name":"percentage_prizes_won_by_women","title":"Percentage prizes won by women","type":"number","rdfType":"http://www.w3.org/2001/XMLSchema#decimal","dwSourceId":"percentage_prizes_won_by_women"},{"name":"percentage_prizes_won_by_men","title":"Percentage prizes won by men","type":"number","rdfType":"http://www.w3.org/2001/XMLSchema#decimal","dwSourceId":"percentage_prizes_won_by_men"},{"name":"remove_average_female_winners_all_countries","title":"REMOVE Average Female Winners (All Countries)","type":"number","rdfType":"http://www.w3.org/2001/XMLSchema#decimal","dwSourceId":"remove_average_female_winners_all_countries"},{"name":"remove_average_female_winners_all_countries_2","title":"REMOVE Average Female Winners (All Countries) (%)","type":"number","rdfType":"http://www.w3.org/2001/XMLSchema#decimal","dwSourceId":"remove_average_female_winners_all_countries_2"}]},"path":"data/countries.csv","format":"csv"},{"name":"prizes","schema":{"fields":[{"name":"id","title":"ID","type":"string","rdfType":"http://www.w3.org/2001/XMLSchema#string","dwSourceId":"id"},{"name":"year","title":"Year","type":"gyear","rdfType":"http://www.w3.org/2001/XMLSchema#gYear","dwSourceId":"year"},{"name":"award","title":"Award","type":"string","rdfType":"http://www.w3.org/2001/XMLSchema#string","dwSourceId":"award"},{"name":"winner","title":"Winner","type":"string","rdfType":"http://www.w3.org/2001/XMLSchema#string","dwSourceId":"winner"},{"name":"award_motivation","title":"Award Motivation","type":"string","rdfType":"http://www.w3.org/2001/XMLSchema#string","dwSourceId":"award_motivation"},{"name":"link_on_official_website","title":"Link on official website","type":"string","rdfType":"http://www.w3.org/2001/XMLSchema#anyURI","dwSourceId":"link_on_official_website"}]},"path":"data/prizes.csv","format":"csv"},{"name":"winners","schema":{"fields":[{"name":"winner","title":"Winner","type":"string","rdfType":"http://www.w3.org/2001/XMLSchema#string","dwSourceId":"winner"},{"name":"http_upload_wikimedia_org_wikipedia_commons_6_6e_kailash_satyarthi_jpg","title":"http://upload.wikimedia.org/wikipedia/commons/6/6e/Kailash_Satyarthi.jpg","type":"string","rdfType":"http://www.w3.org/2001/XMLSchema#string","dwSourceId":"http_upload_wikimedia_org_wikipedia_commons_6_6e_kailash_satyarthi_jpg"},{"name":"known_for","title":"Known For","type":"string","rdfType":"http://www.w3.org/2001/XMLSchema#string","dwSourceId":"known_for"},{"name":"field","title":"Field","type":"string","rdfType":"http://www.w3.org/2001/XMLSchema#string","dwSourceId":"field"},{"name":"gender","title":"Gender","type":"string","rdfType":"http://www.w3.org/2001/XMLSchema#string","dwSourceId":"gender"},{"name":"place_of_birth","title":"Place of Birth","type":"string","rdfType":"http://www.w3.org/2001/XMLSchema#string","dwSourceId":"place_of_birth"},{"name":"country_of_birth","title":"Country of Birth","type":"string","rdfType":"http://www.w3.org/2001/XMLSchema#string","dwSourceId":"country_of_birth"},{"name":"short_description","title":"Short Description","type":"string","rdfType":"http://www.w3.org/2001/XMLSchema#string","dwSourceId":"short_description"},{"name":"description","title":"Description","type":"string","rdfType":"http://www.w3.org/2001/XMLSchema#string","dwSourceId":"description"},{"name":"year_of_birth","title":"Year of Birth","type":"integer","rdfType":"http://www.w3.org/2001/XMLSchema#integer","dwSourceId":"year_of_birth"},{"name":"age_of_nobel_win","title":"Age of Nobel Win","type":"integer","rdfType":"http://www.w3.org/2001/XMLSchema#integer","dwSourceId":"age_of_nobel_win"},{"name":"universities","title":"Universities","type":"string","rdfType":"http://www.w3.org/2001/XMLSchema#string","dwSourceId":"universities"},{"name":"country_represented_for_nobel_prize","title":"Country represented for Nobel Prize","type":"string","rdfType":"http://www.w3.org/2001/XMLSchema#string","dwSourceId":"country_represented_for_nobel_prize"},{"name":"image","title":"Image","type":"string","rdfType":"http://www.w3.org/2001/XMLSchema#anyURI","dwSourceId":"image"},{"name":"dbpedia_link","title":"DBpedia Link","type":"string","rdfType":"http://www.w3.org/2001/XMLSchema#anyURI","dwSourceId":"dbpedia_link"},{"name":"profile","title":"Profile","type":"string","rdfType":"http://www.w3.org/2001/XMLSchema#anyURI","dwSourceId":"profile"}]},"path":"data/winners.csv","format":"csv"},{"name":"years","schema":{"fields":[{"name":"year","title":"Year","type":"gyear","rdfType":"http://www.w3.org/2001/XMLSchema#gYear","dwSourceId":"year"},{"name":"average_age_of_laureates","title":"Average age of laureates","type":"integer","rdfType":"http://www.w3.org/2001/XMLSchema#integer","dwSourceId":"average_age_of_laureates"},{"name":"prizes_won_by_women","title":"Prizes won by women","type":"integer","rdfType":"http://www.w3.org/2001/XMLSchema#integer","dwSourceId":"prizes_won_by_women"},{"name":"prizes_won_by_men","title":"Prizes won by men","type":"integer","rdfType":"http://www.w3.org/2001/XMLSchema#integer","dwSourceId":"prizes_won_by_men"},{"name":"percentage_prizes_won_by_women","title":"Percentage prizes won by women","type":"number","rdfType":"http://www.w3.org/2001/XMLSchema#decimal","dwSourceId":"percentage_prizes_won_by_women"},{"name":"percentage_prizes_won_by_men","title":"Percentage prizes won by men","type":"number","rdfType":"http://www.w3.org/2001/XMLSchema#decimal","dwSourceId":"percentage_prizes_won_by_men"},{"name":"remove_average_female_winners_1901_2014","title":"REMOVE Average Female Winners (1901 - 2014)","type":"number","rdfType":"http://www.w3.org/2001/XMLSchema#decimal","dwSourceId":"remove_average_female_winners_1901_2014"},{"name":"remove_average_female_winners_1901_2014_2","title":"REMOVE Average Female Winners (1901 - 2014) (%)","type":"number","rdfType":"http://www.w3.org/2001/XMLSchema#decimal","dwSourceId":"remove_average_female_winners_1901_2014_2"}]},"path":"data/years.csv","format":"csv"},{"name":"original/Award Categories.csv","path":"original/Award Categories.csv","format":"csv","mediatype":"text/csv","bytes":437},{"name":"original/Countries.csv","path":"original/Countries.csv","format":"csv","mediatype":"text/csv","bytes":2997},{"name":"original/Prizes.csv","path":"original/Prizes.csv","format":"csv","mediatype":"text/csv","bytes":126446},{"name":"original/Winners.csv","path":"original/Winners.csv","format":"csv","mediatype":"text/csv","bytes":659972},{"name":"original/Years.csv","path":"original/Years.csv","format":"csv","mediatype":"text/csv","bytes":3234}]}